{"2009":3,"2017":3,"div":22,"JavaScript":11,"isdisabled":11,"onyour":11,"browser":11,"Skip":5,"navigation":9,"links":5,"Overview":5,"Package":21,"Class":18,"Use":7,"Tree":7,"Deprecated":7,"Index":7,"Help":3,"Prev":5,"Next":7,"Frames":10,"No":7,"All":8,"Classes":6,"SEARCH":5,"org":3,"jsoup":3,"safety":1,"Contains":2,"thejsoup":3,"HTML":12,"cleaner":21,"andwhitelist":3,"definitions":3,"Summary":5,"Description":5,"Cleaner":6,"The":8,"whitelist":9,"based":9,"Whitelist":7,"Whitelists":8,"define":9,"whatHTML":9,"elements":9,"andattributes":9,"toallow":9,"throughthe":9,"Copyright":3,"Jonathan":4,"Hedley":3,"rights":3,"reserved":3,"HelpSkip":2,"linksSkip":2,"linksOverview":2,"HelpOverviewOverviewPackageClassUseUseTreeTreeDeprecatedDeprecatedIndexIndexHelpHelpPrev":2,"PackagePrev":4,"PackageNext":4,"PackageFrames":2,"FramesFramesFramesNo":2,"FramesNo":2,"FramesAll":2,"ClassesAll":4,"ClassesSEARCH":1,"safetyPackage":1,"safetyContains":1,"SummaryClass":2,"DescriptionClass":1,"DescriptionClassDescriptionCleaner":1,"CleanerCleanerThe":1,"WhitelistWhitelistWhitelists":1}